curve_fits/__init__.py
curve_fits/fits.py
curve_fits/frames.py
tests/__init__.py
tests/test_common.py
tests/test_fits.py
tests/test_tcp.py
curve_fits-1.0.dev3.dist-info/LICENSE
curve_fits-1.0.dev3.dist-info/METADATA
curve_fits-1.0.dev3.dist-info/WHEEL
curve_fits-1.0.dev3.dist-info/top_level.txt
curve_fits-1.0.dev3.dist-info/RECORD
